include/mlx/data/Array.h
include/mlx/data/Buffer.h
include/mlx/data/Dataset.h
include/mlx/data/Sample.h
include/mlx/data/Stream.h
include/mlx/data/buffer/Append.h
include/mlx/data/buffer/Batch.h
include/mlx/data/buffer/Buffer.h
include/mlx/data/buffer/DynamicBatch.h
include/mlx/data/buffer/FilesFromTAR.h
include/mlx/data/buffer/FromStream.h
include/mlx/data/buffer/FromVector.h
include/mlx/data/buffer/Partition.h
include/mlx/data/buffer/Perm.h
include/mlx/data/buffer/Shuffle.h
include/mlx/data/buffer/Transform.h
include/mlx/data/core/AWSFileFetcher.h
include/mlx/data/core/BPETokenizer.h
include/mlx/data/core/BatchShape.h
include/mlx/data/core/CSVReader.h
include/mlx/data/core/FileFetcher.h
include/mlx/data/core/Graph.h
include/mlx/data/core/Levenshtein.h
include/mlx/data/core/Numpy.h
include/mlx/data/core/State.h
include/mlx/data/core/TARReader.h
include/mlx/data/core/ThreadController.h
include/mlx/data/core/ThreadPool.h
include/mlx/data/core/Tokenizer.h
include/mlx/data/core/Trie.h
include/mlx/data/core/Utils.h
include/mlx/data/core/Version.h
include/mlx/data/core/imemstream.h
include/mlx/data/core/audio/Audio.h
include/mlx/data/core/audio/AudioPrivate.h
include/mlx/data/core/image/Image.h
include/mlx/data/core/image/ImagePrivate.h
include/mlx/data/core/video/Video.h
include/mlx/data/core/video/VideoPrivate.h
include/mlx/data/op/FilterByShape.h
include/mlx/data/op/FilterKey.h
include/mlx/data/op/ImageTransform.h
include/mlx/data/op/KeyTransform.h
include/mlx/data/op/LoadAudio.h
include/mlx/data/op/LoadFile.h
include/mlx/data/op/LoadImage.h
include/mlx/data/op/LoadNumpy.h
include/mlx/data/op/LoadVideo.h
include/mlx/data/op/Op.h
include/mlx/data/op/Pad.h
include/mlx/data/op/ReadFromTAR.h
include/mlx/data/op/RemoveValue.h
include/mlx/data/op/RenameKey.h
include/mlx/data/op/Replace.h
include/mlx/data/op/SampleTransform.h
include/mlx/data/op/SaveImage.h
include/mlx/data/op/Shape.h
include/mlx/data/op/Shard.h
include/mlx/data/op/Slice.h
include/mlx/data/op/Squeeze.h
mlx_data-0.2.0.dist-info/licenses/LICENSE
mlx_data-0.2.0.dist-info/METADATA
mlx_data-0.2.0.dist-info/WHEEL
mlx_data-0.2.0.dist-info/top_level.txt
mlx_data-0.2.0.dist-info/RECORD
