Metadata-Version: 2.4
Name: mlx-data
Version: 0.2.0
Summary: Universal data loaders
Home-page: https://github.com/ml-explore/mlx-data
Author: Ronan Collobert
Author-email: collobert@apple.com
License: MIT
License-File: LICENSE
Requires-Dist: numpy
Dynamic: author
Dynamic: author-email
Dynamic: home-page
Dynamic: license
Dynamic: license-file
Dynamic: requires-dist
Dynamic: summary
